CHANGES.rst
CONTRIBUTORS.rst
DEVELOP.rst
DEVELOP_THEME.rst
LICENSE.GPL
LICENSE.rst
MANIFEST.in
README.rst
requirements.txt
setup.cfg
setup.py
docs/LICENSE.GPL
docs/LICENSE.rst
docs/index.rst
src/imioweb/__init__.py
src/imioweb.theme.egg-info/PKG-INFO
src/imioweb.theme.egg-info/SOURCES.txt
src/imioweb.theme.egg-info/dependency_links.txt
src/imioweb.theme.egg-info/entry_points.txt
src/imioweb.theme.egg-info/namespace_packages.txt
src/imioweb.theme.egg-info/not-zip-safe
src/imioweb.theme.egg-info/requires.txt
src/imioweb.theme.egg-info/top_level.txt
src/imioweb/theme/__init__.py
src/imioweb/theme/configure.zcml
src/imioweb/theme/interfaces.py
src/imioweb/theme/setuphandlers.py
src/imioweb/theme/testing.py
src/imioweb/theme/browser/__init__.py
src/imioweb/theme/browser/configure.zcml
src/imioweb/theme/browser/migrate_to_plone52.py
src/imioweb/theme/browser/overrides/.gitkeep
src/imioweb/theme/browser/static/.gitkeep
src/imioweb/theme/locales/update.sh
src/imioweb/theme/profiles/default/browserlayer.xml
src/imioweb/theme/profiles/default/metadata.xml
src/imioweb/theme/profiles/default/registry.xml
src/imioweb/theme/profiles/default/theme.xml
src/imioweb/theme/profiles/uninstall/browserlayer.xml
src/imioweb/theme/profiles/uninstall/theme.xml
src/imioweb/theme/tests/__init__.py
src/imioweb/theme/tests/test_robot.py
src/imioweb/theme/tests/test_setup.py
src/imioweb/theme/tests/robot/test_example.robot
src/imioweb/theme/theme/index.html
src/imioweb/theme/theme/manifest.cfg
src/imioweb/theme/theme/package.json
src/imioweb/theme/theme/rules.xml
src/imioweb/theme/theme/barceloneta/BARCELONETA-UPDATE.rst
src/imioweb/theme/theme/barceloneta/BARCELONETA-VERSION.rst
src/imioweb/theme/theme/barceloneta/backend.xml
src/imioweb/theme/theme/barceloneta/barceloneta-apple-touch-icon-114x114-precomposed.png
src/imioweb/theme/theme/barceloneta/barceloneta-apple-touch-icon-144x144-precomposed.png
src/imioweb/theme/theme/barceloneta/barceloneta-apple-touch-icon-57x57-precomposed.png
src/imioweb/theme/theme/barceloneta/barceloneta-apple-touch-icon-72x72-precomposed.png
src/imioweb/theme/theme/barceloneta/barceloneta-apple-touch-icon-precomposed.png
src/imioweb/theme/theme/barceloneta/barceloneta-apple-touch-icon.png
src/imioweb/theme/theme/barceloneta/barceloneta-favicon.ico
